{
  "id": "13SEQHFmr3P4XIrrKJmL9J",
  "name": "13",
  "tracks": [
    {
      "id": "1X9f904unWw1il1AZ1XtNE",
      "name": "Mykonos",
      "artists": [
        {
          "id": "1Om8dYusTC6D8oEBzGNfi3",
          "name": "ELISHIA"
        },
        {
          "id": "4eynUvqfhXYhmWc0QxKuiE",
          "name": "PATØN"
        }
      ],
      "addedAt": "2021-04-29T12:49:53Z"
    },
    {
      "id": "1iG0qH5EesfjYu8h9d62Fp",
      "name": "Unfold",
      "artists": [
        {
          "id": "00CYRdkMnA0mwfy1VQPA7X",
          "name": "Ellis"
        },
        {
          "id": "77YCAroJisD7uOECsiPcAL",
          "name": "Tamzene"
        }
      ],
      "addedAt": "2021-04-30T14:39:24Z"
    },
    {
      "id": "53kWAAfx7IopXRa31MQHB8",
      "name": "Good Vibes",
      "artists": [
        {
          "id": "28y6CyJNkGNjJQKrlx4AmN",
          "name": "HRVY"
        },
        {
          "id": "4YXycRbyyAE0wozTk7QMEq",
          "name": "Matoma"
        }
      ],
      "addedAt": "2021-05-04T18:25:49Z"
    },
    {
      "id": "1cVQmBnSLjhWB67iqAXYZZ",
      "name": "I Just Wanna (feat. Bow Anderson)",
      "artists": [
        {
          "id": "4bL2B6hmLlMWnUEZnorEtG",
          "name": "Felix Jaehn"
        },
        {
          "id": "7DMveApC7UnC2NPfPvlHSU",
          "name": "Cheat Codes"
        },
        {
          "id": "6ObN9YNBliscJOImQp4UZO",
          "name": "Bow Anderson"
        }
      ],
      "addedAt": "2021-05-04T18:28:38Z"
    },
    {
      "id": "67hW1sjylJ8EMXAguJ68i1",
      "name": "Nothing Like Wine",
      "artists": [
        {
          "id": "75rnylco41xve8uPYbEZbc",
          "name": "Velee"
        },
        {
          "id": "3eSiyfI9xykA5QtgcLS43b",
          "name": "Emmi"
        }
      ],
      "addedAt": "2021-05-06T09:58:50Z"
    },
    {
      "id": "6j1moieTiZkftkKpiilSCH",
      "name": "DEAD",
      "artists": [
        {
          "id": "0okpgBQamDqOZazBeH0J3I",
          "name": "Unknown Brain"
        },
        {
          "id": "5GTYEYJqmYH3VlaRRnkaWj",
          "name": "Kazhi"
        }
      ],
      "addedAt": "2021-09-28T16:21:40Z"
    },
    {
      "id": "0ROL0ZWCApzHUuqIPgNtae",
      "name": "black mirror - MARS Remix",
      "artists": [
        {
          "id": "5fgeISV9AWkZHomodJZtXt",
          "name": "MARS"
        },
        {
          "id": "3zXPbW06DXFBAToUstfD1V",
          "name": "NOT THE MAIN CHARACTERS"
        }
      ],
      "addedAt": "2021-09-28T16:24:04Z"
    },
    {
      "id": "2YhF6jwopT55f7mKQynoQq",
      "name": "24 Hours x Gypsy Woman (feat. Yasmin Green, Crystal Waters & Bougenvilla ) [VIP Mash-up]",
      "artists": [
        {
          "id": "6MDME20pz9RveH9rEXvrOM",
          "name": "Clean Bandit"
        },
        {
          "id": "2sd9Q3r0Jhqpe3w9WVuG43",
          "name": "Crystal Waters"
        },
        {
          "id": "1I5pYXplsbqmHaVWlAEhla",
          "name": "Bougenvilla"
        },
        {
          "id": "2UWEzvq7cBIcPt5Z9AwD1Y",
          "name": "Yasmin Green"
        }
      ],
      "addedAt": "2021-09-28T16:26:24Z"
    },
    {
      "id": "6lAtL6RaWe30sRuSFjKWQt",
      "name": "Sit like a Flamingo",
      "artists": [
        {
          "id": "64N3o9z76C2APyfgQV2HMp",
          "name": "Half an Orange"
        },
        {
          "id": "0YVFdCm1S3ikQU0yl110lu",
          "name": "Disero"
        },
        {
          "id": "2MbO01KZTMshiRXcOLo88R",
          "name": "Josh Bogert"
        }
      ],
      "addedAt": "2021-09-28T16:29:34Z"
    },
    {
      "id": "5q7AR3TkyCxlgxAjBMu4yL",
      "name": "Therapy",
      "artists": [
        {
          "id": "1BAdSa5cdtCNLbvT7gWmtJ",
          "name": "Conro"
        }
      ],
      "addedAt": "2021-09-28T16:32:53Z"
    },
    {
      "id": "0MpT0XzhoZPJV2kYf9I0r5",
      "name": "Awesome",
      "artists": [
        {
          "id": "2L2hppNg0A5WfGJTChIJL5",
          "name": "Dylan Rockoff"
        }
      ],
      "addedAt": "2021-09-28T16:35:56Z"
    },
    {
      "id": "43wuszNrHgfr3JXaJ5u4tR",
      "name": "Like That",
      "artists": [
        {
          "id": "7xBGi7Eign0fX7jGQj5KlJ",
          "name": "GRACEY"
        },
        {
          "id": "6sFHvCyqklnJpXC9Nh1aag",
          "name": "Alexander 23"
        }
      ],
      "addedAt": "2021-09-28T16:38:46Z"
    },
    {
      "id": "0riVKRa5xqaNCV6qpKpVls",
      "name": "Stupid as You",
      "artists": [
        {
          "id": "2bOcFoSypJcNgs5IaXVKMp",
          "name": "Katnip"
        },
        {
          "id": "3y3turaJpe5Lpmuc9Uhhfo",
          "name": "Asta"
        }
      ],
      "addedAt": "2021-09-28T16:42:42Z"
    },
    {
      "id": "7lFLtG8AOte0NDGbp14H31",
      "name": "One Day Left",
      "artists": [
        {
          "id": "1l2NYhptmHjo64MDOcej1x",
          "name": "LOVA"
        }
      ],
      "addedAt": "2021-09-29T02:17:50Z"
    },
    {
      "id": "1Wr6zfVnj5dRVC4Xqf8ZZY",
      "name": "Alibi",
      "artists": [
        {
          "id": "01amjyTlohCQrBLbM1scoO",
          "name": "Distrion"
        },
        {
          "id": "71GRU9wS94BTdNwQWRMJV6",
          "name": "Heleen"
        }
      ],
      "addedAt": "2021-10-02T17:39:49Z"
    }
  ]
}